{"name":"Arbok","abilities":[{"name":"intimidate","description":""},{"name":"shed-skin","description":""},{"name":"unnerve","description":""}],"attack":85,"defense":69,"speed":80,"hp":60,"sp_atk":65,"sp_def":79,"total":0,"types":[{"name":"poison"}],"moves":[{"name":"Bind","type":"Normal","category":"Physical","power":15,"accuracy":85,"pp":20,"description":"Traps opponent, damaging them for 4-5 turns."},{"name":"Spite","type":"Ghost","category":"Status","power":-1,"accuracy":100,"pp":10,"description":"The opponent's last move loses 2-5 PP."},{"name":"Rock Tomb","type":"Rock","category":"Physical","power":60,"accuracy":95,"pp":15,"description":"Lowers opponent's Speed."},{"name":"Crunch","type":"Dark","category":"Physical","power":80,"accuracy":100,"pp":15,"description":"May lower opponent's Defense."},{"name":"Secret Power","type":"Normal","category":"Physical","power":70,"accuracy":100,"pp":20,"description":"Effects of the attack vary with the location."},{"name":"Snatch","type":"Dark","category":"Status","power":-1,"accuracy":-1,"pp":10,"description":"Steals the effects of the opponent's next move."},{"name":"Facade","type":"Normal","category":"Physical","power":70,"accuracy":100,"pp":20,"description":"Power doubles if user is burned, poisoned, or paralyzed."},{"name":"Torment","type":"Dark","category":"Status","power":-1,"accuracy":100,"pp":15,"description":"Opponent cannot use the same move in a row."},{"name":"Swallow","type":"Normal","category":"Status","power":-1,"accuracy":-1,"pp":10,"description":"The more times the user has performed Stockpile, the more HP is recovered."},{"name":"Spit Up","type":"Normal","category":"Special","power":-1,"accuracy":100,"pp":10,"description":"Power depends on how many times the user performed Stockpile."},{"name":"Stockpile","type":"Normal","category":"Status","power":-1,"accuracy":-1,"pp":20,"description":"Stores energy for use with Spit Up and Swallow."},{"name":"Rain Dance","type":"Water","category":"Status","power":-1,"accuracy":-1,"pp":5,"description":"Makes it rain for 5 turns."},{"name":"Iron Tail","type":"Steel","category":"Physical","power":100,"accuracy":75,"pp":15,"description":"May lower opponent's Defense."},{"name":"Sunny Day","type":"Fire","category":"Status","power":-1,"accuracy":-1,"pp":5,"description":"Makes it sunny for 5 turns."},{"name":"Hidden Power","type":"Normal","category":"Special","power":60,"accuracy":100,"pp":15,"description":"Type and power depends on user's IVs."},{"name":"Frustration","type":"Normal","category":"Physical","power":-1,"accuracy":100,"pp":20,"description":"Power decreases with higher Happiness."},{"name":"Return","type":"Normal","category":"Physical","power":-1,"accuracy":100,"pp":20,"description":"Power increases with user's Happiness."},{"name":"Sleep Talk","type":"Normal","category":"Status","power":-1,"accuracy":-1,"pp":10,"description":"User performs one of its own moves while sleeping."},{"name":"Attract","type":"Normal","category":"Status","power":-1,"accuracy":100,"pp":15,"description":"If opponent is the opposite gender, it's less likely to attack."},{"name":"Swagger","type":"Normal","category":"Status","power":-1,"accuracy":90,"pp":15,"description":"Opponent becomes confused, but its Attack is raised two stages."},{"name":"Endure","type":"Normal","category":"Status","power":-1,"accuracy":-1,"pp":10,"description":"Always left with at least 1 HP, but may fail if used consecutively."},{"name":"Giga Drain","type":"Grass","category":"Special","power":75,"accuracy":100,"pp":10,"description":"User recovers half the HP inflicted on opponent."},{"name":"Sludge Bomb","type":"Poison","category":"Special","power":90,"accuracy":100,"pp":10,"description":"May poison opponent."},{"name":"Protect","type":"Normal","category":"Status","power":-1,"accuracy":-1,"pp":10,"description":"User is not affected by opponent's move."},{"name":"Curse","type":"Ghost","category":"Status","power":-1,"accuracy":-1,"pp":10,"description":"Ghosts lose 50% of max HP and curse the opponent; Non-Ghosts raise Attack, Defense and lower Speed."},{"name":"Snore","type":"Normal","category":"Special","power":50,"accuracy":100,"pp":15,"description":"Can only be used if asleep. May cause flinching."},{"name":"Thief","type":"Dark","category":"Physical","power":60,"accuracy":100,"pp":25,"description":"Also steals opponent's held item."},{"name":"Haze","type":"Ice","category":"Status","power":-1,"accuracy":-1,"pp":30,"description":"Resets all stat changes."},{"name":"Headbutt","type":"Normal","category":"Physical","power":70,"accuracy":100,"pp":15,"description":"May cause flinching."},{"name":"Substitute","type":"Normal","category":"Status","power":-1,"accuracy":-1,"pp":10,"description":"Uses HP to creates a decoy that takes hits."},{"name":"Rock Slide","type":"Rock","category":"Physical","power":75,"accuracy":90,"pp":10,"description":"May cause flinching."},{"name":"Rest","type":"Psychic","category":"Status","power":-1,"accuracy":-1,"pp":10,"description":"User sleeps for 2 turns, but user is fully healed."},{"name":"Glare","type":"Normal","category":"Status","power":-1,"accuracy":100,"pp":30,"description":"Paralyzes opponent."},{"name":"Skull Bash","type":"Normal","category":"Physical","power":130,"accuracy":100,"pp":10,"description":"Raises Defense on first turn, attacks on second."},{"name":"Bide","type":"Normal","category":"Physical","power":-1,"accuracy":-1,"pp":10,"description":"User takes damage for two turns then strikes back double."},{"name":"Double Team","type":"Normal","category":"Status","power":-1,"accuracy":-1,"pp":15,"description":"Raises user's Evasiveness."},{"name":"Screech","type":"Normal","category":"Status","power":-1,"accuracy":85,"pp":40,"description":"Sharply lowers opponent's Defense."},{"name":"Mimic","type":"Normal","category":"Status","power":-1,"accuracy":-1,"pp":10,"description":"Copies the opponent's last move."},{"name":"Rage","type":"Normal","category":"Physical","power":20,"accuracy":100,"pp":20,"description":"Raises user's Attack when hit."},{"name":"Toxic","type":"Poison","category":"Status","power":-1,"accuracy":90,"pp":10,"description":"Badly poisons opponent."},{"name":"Dig","type":"Ground","category":"Physical","power":80,"accuracy":100,"pp":10,"description":"Digs underground on first turn, attacks on second. Can also escape from caves."},{"name":"Fissure","type":"Ground","category":"Physical","power":-1,"accuracy":-1,"pp":5,"description":"One-Hit-KO, if it hits."},{"name":"Earthquake","type":"Ground","category":"Physical","power":100,"accuracy":100,"pp":10,"description":"Power is doubled if opponent is underground from using Dig."},{"name":"Mega Drain","type":"Grass","category":"Special","power":40,"accuracy":100,"pp":15,"description":"User recovers half the HP inflicted on opponent."},{"name":"Strength","type":"Normal","category":"Physical","power":80,"accuracy":100,"pp":15,"description":""},{"name":"Hyper Beam","type":"Normal","category":"Special","power":150,"accuracy":90,"pp":5,"description":"User must recharge next turn."},{"name":"Acid","type":"Poison","category":"Special","power":40,"accuracy":100,"pp":30,"description":"May lower opponent's Special Defense."},{"name":"Bite","type":"Dark","category":"Physical","power":60,"accuracy":100,"pp":25,"description":"May cause flinching."},{"name":"Leer","type":"Normal","category":"Status","power":-1,"accuracy":100,"pp":30,"description":"Lowers opponent's Defense."},{"name":"Poison Sting","type":"Poison","category":"Physical","power":15,"accuracy":100,"pp":35,"description":"May poison the opponent."},{"name":"Double-Edge","type":"Normal","category":"Physical","power":120,"accuracy":100,"pp":15,"description":"User receives recoil damage."},{"name":"Take Down","type":"Normal","category":"Physical","power":90,"accuracy":85,"pp":20,"description":"User receives recoil damage."},{"name":"Wrap","type":"Normal","category":"Physical","power":15,"accuracy":90,"pp":20,"description":"Traps opponent, damaging them for 4-5 turns."},{"name":"Body Slam","type":"Normal","category":"Physical","power":85,"accuracy":100,"pp":15,"description":"May paralyze opponent."}]}