{"name":"Wailord","abilities":[{"name":"oblivious","description":""},{"name":"water-veil","description":""},{"name":"pressure","description":""}],"attack":90,"defense":45,"speed":60,"hp":170,"sp_atk":90,"sp_def":45,"total":0,"types":[{"name":"water"}],"moves":[{"name":"Hyper Voice","type":"Normal","category":"Special","power":90,"accuracy":100,"pp":10,"description":""},{"name":"Block","type":"Normal","category":"Status","power":-1,"accuracy":-1,"pp":5,"description":"Opponent cannot flee or switch."},{"name":"Headbutt","type":"Normal","category":"Physical","power":70,"accuracy":100,"pp":15,"description":"May cause flinching."},{"name":"Bounce","type":"Flying","category":"Physical","power":85,"accuracy":85,"pp":5,"description":"Springs up on first turn, attacks on second. May paralyze opponent."},{"name":"Sleep Talk","type":"Normal","category":"Status","power":-1,"accuracy":-1,"pp":10,"description":"User performs one of its own moves while sleeping."},{"name":"Swagger","type":"Normal","category":"Status","power":-1,"accuracy":90,"pp":15,"description":"Opponent becomes confused, but its Attack is raised two stages."},{"name":"Endure","type":"Normal","category":"Status","power":-1,"accuracy":-1,"pp":10,"description":"Always left with at least 1 HP, but may fail if used consecutively."},{"name":"Icy Wind","type":"Ice","category":"Special","power":55,"accuracy":95,"pp":15,"description":"Lowers opponent's Speed."},{"name":"Snore","type":"Normal","category":"Special","power":50,"accuracy":100,"pp":15,"description":"Can only be used if asleep. May cause flinching."},{"name":"Substitute","type":"Normal","category":"Status","power":-1,"accuracy":-1,"pp":10,"description":"Uses HP to creates a decoy that takes hits."},{"name":"Defense Curl","type":"Normal","category":"Status","power":-1,"accuracy":-1,"pp":40,"description":"Raises user's Defense."},{"name":"Mimic","type":"Normal","category":"Status","power":-1,"accuracy":-1,"pp":10,"description":"Copies the opponent's last move."},{"name":"Double-Edge","type":"Normal","category":"Physical","power":120,"accuracy":100,"pp":15,"description":"User receives recoil damage."},{"name":"Body Slam","type":"Normal","category":"Physical","power":85,"accuracy":100,"pp":15,"description":"May paralyze opponent."},{"name":"Water Pulse","type":"Water","category":"Special","power":60,"accuracy":100,"pp":20,"description":"May confuse opponent."},{"name":"Water Spout","type":"Water","category":"Special","power":150,"accuracy":100,"pp":5,"description":"The higher the user's HP, the higher the damage caused."},{"name":"Rock Tomb","type":"Rock","category":"Physical","power":60,"accuracy":95,"pp":15,"description":"Lowers opponent's Speed."},{"name":"Astonish","type":"Ghost","category":"Physical","power":30,"accuracy":100,"pp":15,"description":"May cause flinching."},{"name":"Dive","type":"Water","category":"Physical","power":80,"accuracy":100,"pp":10,"description":"Dives underwater on first turn, attacks on second turn."},{"name":"Secret Power","type":"Normal","category":"Physical","power":70,"accuracy":100,"pp":20,"description":"Effects of the attack vary with the location."},{"name":"Facade","type":"Normal","category":"Physical","power":70,"accuracy":100,"pp":20,"description":"Power doubles if user is burned, poisoned, or paralyzed."},{"name":"Hail","type":"Ice","category":"Status","power":-1,"accuracy":-1,"pp":10,"description":"Non-Ice types are damaged for 5 turns."},{"name":"Whirlpool","type":"Water","category":"Special","power":35,"accuracy":85,"pp":15,"description":"Traps opponent, damaging them for 4-5 turns."},{"name":"Rock Smash","type":"Fighting","category":"Physical","power":40,"accuracy":100,"pp":15,"description":"May lower opponent's Defense."},{"name":"Rain Dance","type":"Water","category":"Status","power":-1,"accuracy":-1,"pp":5,"description":"Makes it rain for 5 turns."},{"name":"Hidden Power","type":"Normal","category":"Special","power":60,"accuracy":100,"pp":15,"description":"Type and power depends on user's IVs."},{"name":"Frustration","type":"Normal","category":"Physical","power":-1,"accuracy":100,"pp":20,"description":"Power decreases with higher Happiness."},{"name":"Return","type":"Normal","category":"Physical","power":-1,"accuracy":100,"pp":20,"description":"Power increases with user's Happiness."},{"name":"Attract","type":"Normal","category":"Status","power":-1,"accuracy":100,"pp":15,"description":"If opponent is the opposite gender, it's less likely to attack."},{"name":"Rollout","type":"Rock","category":"Physical","power":30,"accuracy":90,"pp":20,"description":"Doubles in power each turn for 5 turns."},{"name":"Protect","type":"Normal","category":"Status","power":-1,"accuracy":-1,"pp":10,"description":"User is not affected by opponent's move."},{"name":"Rest","type":"Psychic","category":"Status","power":-1,"accuracy":-1,"pp":10,"description":"User sleeps for 2 turns, but user is fully healed."},{"name":"Splash","type":"Normal","category":"Status","power":-1,"accuracy":-1,"pp":40,"description":"Doesn't do ANYTHING."},{"name":"Amnesia","type":"Psychic","category":"Status","power":-1,"accuracy":-1,"pp":20,"description":"Sharply raises user's Special Defense."},{"name":"Waterfall","type":"Water","category":"Physical","power":80,"accuracy":100,"pp":15,"description":"May cause flinching."},{"name":"Double Team","type":"Normal","category":"Status","power":-1,"accuracy":-1,"pp":15,"description":"Raises user's Evasiveness."},{"name":"Toxic","type":"Poison","category":"Status","power":-1,"accuracy":90,"pp":10,"description":"Badly poisons opponent."},{"name":"Earthquake","type":"Ground","category":"Physical","power":100,"accuracy":100,"pp":10,"description":"Power is doubled if opponent is underground from using Dig."},{"name":"Strength","type":"Normal","category":"Physical","power":80,"accuracy":100,"pp":15,"description":""},{"name":"Hyper Beam","type":"Normal","category":"Special","power":150,"accuracy":90,"pp":5,"description":"User must recharge next turn."},{"name":"Blizzard","type":"Ice","category":"Special","power":110,"accuracy":70,"pp":5,"description":"May freeze opponent."},{"name":"Ice Beam","type":"Ice","category":"Special","power":90,"accuracy":100,"pp":10,"description":"May freeze opponent."},{"name":"Surf","type":"Water","category":"Special","power":90,"accuracy":100,"pp":15,"description":"Hits all adjacent Pokémon."},{"name":"Hydro Pump","type":"Water","category":"Special","power":110,"accuracy":80,"pp":5,"description":""},{"name":"Water Gun","type":"Water","category":"Special","power":40,"accuracy":100,"pp":25,"description":""},{"name":"Mist","type":"Ice","category":"Status","power":-1,"accuracy":-1,"pp":30,"description":"User's stats cannot be changed for a period of time."},{"name":"Roar","type":"Normal","category":"Status","power":-1,"accuracy":-1,"pp":20,"description":"In battles, the opponent switches. In the wild, the Pokémon runs."},{"name":"Growl","type":"Normal","category":"Status","power":-1,"accuracy":100,"pp":40,"description":"Lowers opponent's Attack."}]}