{"aerial ace":{"name":"Aerial Ace","type":"Flying","category":"Physical","power":60,"accuracy":-1,"pp":20,"description":"Ignores Accuracy and Evasiveness."},"air cutter":{"name":"Air Cutter","type":"Flying","category":"Special","power":60,"accuracy":95,"pp":25,"description":"High critical hit ratio."},"arm thrust":{"name":"Arm Thrust","type":"Fighting","category":"Physical","power":15,"accuracy":100,"pp":20,"description":"Hits 2-5 times in one turn."},"aromatherapy":{"name":"Aromatherapy","type":"Grass","category":"Status","power":-1,"accuracy":-1,"pp":5,"description":"Cures all status problems in your party."},"assist":{"name":"Assist","type":"Normal","category":"Status","power":-1,"accuracy":-1,"pp":20,"description":"In a Double Battle, user randomly attacks with a partner's move."},"astonish":{"name":"Astonish","type":"Ghost","category":"Physical","power":30,"accuracy":100,"pp":15,"description":"May cause flinching."},"blast burn":{"name":"Blast Burn","type":"Fire","category":"Special","power":150,"accuracy":90,"pp":5,"description":"User must recharge next turn."},"blaze kick":{"name":"Blaze Kick","type":"Fire","category":"Physical","power":85,"accuracy":90,"pp":10,"description":"High critical hit ratio. May burn opponent."},"block":{"name":"Block","type":"Normal","category":"Status","power":-1,"accuracy":-1,"pp":5,"description":"Opponent cannot flee or switch."},"bounce":{"name":"Bounce","type":"Flying","category":"Physical","power":85,"accuracy":85,"pp":5,"description":"Springs up on first turn, attacks on second. May paralyze opponent."},"brick break":{"name":"Brick Break","type":"Fighting","category":"Physical","power":75,"accuracy":100,"pp":15,"description":"Breaks through Reflect and Light Screen barriers."},"bulk up":{"name":"Bulk Up","type":"Fighting","category":"Status","power":-1,"accuracy":-1,"pp":20,"description":"Raises user's Attack and Defense."},"bullet seed":{"name":"Bullet Seed","type":"Grass","category":"Physical","power":25,"accuracy":100,"pp":30,"description":"Hits 2-5 times in one turn."},"calm mind":{"name":"Calm Mind","type":"Psychic","category":"Status","power":-1,"accuracy":-1,"pp":20,"description":"Raises user's Special Attack and Special Defense."},"camouflage":{"name":"Camouflage","type":"Normal","category":"Status","power":-1,"accuracy":-1,"pp":20,"description":"Changes user's type according to the location."},"charge":{"name":"Charge","type":"Electric","category":"Status","power":-1,"accuracy":-1,"pp":20,"description":"Raises user's Special Defense and next Electric move's power increases."},"cosmic power":{"name":"Cosmic Power","type":"Psychic","category":"Status","power":-1,"accuracy":-1,"pp":20,"description":"Raises user's Defense and Special Defense."},"covet":{"name":"Covet","type":"Normal","category":"Physical","power":60,"accuracy":100,"pp":25,"description":"Opponent's item is stolen by the user."},"crush claw":{"name":"Crush Claw","type":"Normal","category":"Physical","power":75,"accuracy":95,"pp":10,"description":"May lower opponent's Defense."},"dive":{"name":"Dive","type":"Water","category":"Physical","power":80,"accuracy":100,"pp":10,"description":"Dives underwater on first turn, attacks on second turn."},"doom desire":{"name":"Doom Desire","type":"Steel","category":"Special","power":140,"accuracy":100,"pp":5,"description":"Damage occurs 2 turns later."},"dragon claw":{"name":"Dragon Claw","type":"Dragon","category":"Physical","power":80,"accuracy":100,"pp":15,"description":""},"dragon dance":{"name":"Dragon Dance","type":"Dragon","category":"Status","power":-1,"accuracy":-1,"pp":20,"description":"Raises user's Attack and Speed."},"endeavor":{"name":"Endeavor","type":"Normal","category":"Physical","power":-1,"accuracy":100,"pp":5,"description":"Reduces opponent's HP to same as user's."},"eruption":{"name":"Eruption","type":"Fire","category":"Special","power":150,"accuracy":100,"pp":5,"description":"Stronger when the user's HP is higher."},"extrasensory":{"name":"Extrasensory","type":"Psychic","category":"Special","power":80,"accuracy":100,"pp":20,"description":"May cause flinching."},"facade":{"name":"Facade","type":"Normal","category":"Physical","power":70,"accuracy":100,"pp":20,"description":"Power doubles if user is burned, poisoned, or paralyzed."},"fake out":{"name":"Fake Out","type":"Normal","category":"Physical","power":40,"accuracy":100,"pp":10,"description":"User attacks first, foe flinches. Only usable on first turn."},"fake tears":{"name":"Fake Tears","type":"Dark","category":"Status","power":-1,"accuracy":100,"pp":20,"description":"Sharply lowers opponent's Special Defense."},"feather dance":{"name":"Feather Dance","type":"Flying","category":"Status","power":-1,"accuracy":100,"pp":15,"description":"Sharply lowers opponent's Attack."},"flatter":{"name":"Flatter","type":"Dark","category":"Status","power":-1,"accuracy":100,"pp":15,"description":"Confuses opponent, but raises its Special Attack by two stages."},"focus punch":{"name":"Focus Punch","type":"Fighting","category":"Physical","power":150,"accuracy":100,"pp":20,"description":"If the user is hit before attacking, it flinches instead."},"follow me":{"name":"Follow Me","type":"Normal","category":"Status","power":-1,"accuracy":-1,"pp":20,"description":"In Double Battle, the user takes all the attacks."},"frenzy plant":{"name":"Frenzy Plant","type":"Grass","category":"Special","power":150,"accuracy":90,"pp":5,"description":"User must recharge next turn."},"grass whistle":{"name":"Grass Whistle","type":"Grass","category":"Status","power":-1,"accuracy":55,"pp":15,"description":"Puts opponent to sleep."},"grudge":{"name":"Grudge","type":"Ghost","category":"Status","power":-1,"accuracy":-1,"pp":5,"description":"If the users faints after using this move, the PP for the opponent's last move is depleted."},"hail":{"name":"Hail","type":"Ice","category":"Status","power":-1,"accuracy":-1,"pp":10,"description":"Non-Ice types are damaged for 5 turns."},"heat wave":{"name":"Heat Wave","type":"Fire","category":"Special","power":95,"accuracy":90,"pp":10,"description":"May burn opponent."},"helping hand":{"name":"Helping Hand","type":"Normal","category":"Status","power":-1,"accuracy":-1,"pp":20,"description":"In Double Battles, boosts the power of the partner's move."},"howl":{"name":"Howl","type":"Normal","category":"Status","power":-1,"accuracy":-1,"pp":40,"description":"Raises user's Attack."},"hydro cannon":{"name":"Hydro Cannon","type":"Water","category":"Special","power":150,"accuracy":90,"pp":5,"description":"User must recharge next turn."},"hyper voice":{"name":"Hyper Voice","type":"Normal","category":"Special","power":90,"accuracy":100,"pp":10,"description":""},"ice ball":{"name":"Ice Ball","type":"Ice","category":"Physical","power":30,"accuracy":90,"pp":20,"description":"Doubles in power each turn for 5 turns."},"icicle spear":{"name":"Icicle Spear","type":"Ice","category":"Physical","power":25,"accuracy":100,"pp":30,"description":"Hits 2-5 times in one turn."},"imprison":{"name":"Imprison","type":"Psychic","category":"Status","power":-1,"accuracy":-1,"pp":10,"description":"Opponent is unable to use moves that the user also knows."},"ingrain":{"name":"Ingrain","type":"Grass","category":"Status","power":-1,"accuracy":-1,"pp":20,"description":"User restores HP each turn. User cannot escape/switch."},"iron defense":{"name":"Iron Defense","type":"Steel","category":"Status","power":-1,"accuracy":-1,"pp":15,"description":"Sharply raises user's Defense."},"knock off":{"name":"Knock Off","type":"Dark","category":"Physical","power":65,"accuracy":100,"pp":25,"description":"Removes opponent's held item for the rest of the battle."},"leaf blade":{"name":"Leaf Blade","type":"Grass","category":"Physical","power":90,"accuracy":100,"pp":15,"description":"High critical hit ratio."},"luster purge":{"name":"Luster Purge","type":"Psychic","category":"Special","power":70,"accuracy":100,"pp":5,"description":"May lower opponent's Special Defense."},"magic coat":{"name":"Magic Coat","type":"Psychic","category":"Status","power":-1,"accuracy":-1,"pp":15,"description":"Any special move is reflected back to the attacker."},"magical leaf":{"name":"Magical Leaf","type":"Grass","category":"Special","power":60,"accuracy":-1,"pp":20,"description":"Ignores Accuracy and Evasiveness."},"memento":{"name":"Memento","type":"Dark","category":"Status","power":-1,"accuracy":100,"pp":10,"description":"User faints, sharply lowers opponent's Attack and Special Attack."},"metal sound":{"name":"Metal Sound","type":"Steel","category":"Status","power":-1,"accuracy":85,"pp":40,"description":"Sharply lowers opponent's Special Defense."},"meteor mash":{"name":"Meteor Mash","type":"Steel","category":"Physical","power":90,"accuracy":90,"pp":10,"description":"May raise user's Attack."},"mist ball":{"name":"Mist Ball","type":"Psychic","category":"Special","power":70,"accuracy":100,"pp":5,"description":"May lower opponent's Special Attack."},"mud shot":{"name":"Mud Shot","type":"Ground","category":"Special","power":55,"accuracy":95,"pp":15,"description":"Lowers opponent's Speed."},"mud sport":{"name":"Mud Sport","type":"Ground","category":"Status","power":-1,"accuracy":-1,"pp":15,"description":"Weakens the power of Electric-type moves."},"muddy water":{"name":"Muddy Water","type":"Water","category":"Special","power":90,"accuracy":85,"pp":10,"description":"May lower opponent's Accuracy."},"nature power":{"name":"Nature Power","type":"Normal","category":"Status","power":-1,"accuracy":-1,"pp":20,"description":"Uses a certain move based on the current terrain."},"needle arm":{"name":"Needle Arm","type":"Grass","category":"Physical","power":60,"accuracy":100,"pp":15,"description":"May cause flinching."},"odor sleuth":{"name":"Odor Sleuth","type":"Normal","category":"Status","power":-1,"accuracy":-1,"pp":40,"description":"Resets opponent's Evasiveness, Normal-type and Fighting-type attacks can now hit Ghosts, and Ghost-type attacks hit Normal."},"overheat":{"name":"Overheat","type":"Fire","category":"Special","power":130,"accuracy":90,"pp":5,"description":"Sharply lowers user's Special Attack."},"poison fang":{"name":"Poison Fang","type":"Poison","category":"Physical","power":50,"accuracy":100,"pp":15,"description":"May badly poison opponent."},"poison tail":{"name":"Poison Tail","type":"Poison","category":"Physical","power":50,"accuracy":100,"pp":25,"description":"High critical hit ratio. May poison opponent."},"psycho boost":{"name":"Psycho Boost","type":"Psychic","category":"Special","power":140,"accuracy":90,"pp":5,"description":"Sharply lowers user's Special Attack."},"recycle":{"name":"Recycle","type":"Normal","category":"Status","power":-1,"accuracy":-1,"pp":10,"description":"User's used hold item is restored."},"refresh":{"name":"Refresh","type":"Normal","category":"Status","power":-1,"accuracy":-1,"pp":20,"description":"Cures paralysis, poison, and burns."},"revenge":{"name":"Revenge","type":"Fighting","category":"Physical","power":60,"accuracy":100,"pp":10,"description":"Power increases if user was hit first."},"rock blast":{"name":"Rock Blast","type":"Rock","category":"Physical","power":25,"accuracy":90,"pp":10,"description":"Hits 2-5 times in one turn."},"rock tomb":{"name":"Rock Tomb","type":"Rock","category":"Physical","power":60,"accuracy":95,"pp":15,"description":"Lowers opponent's Speed."},"role play":{"name":"Role Play","type":"Psychic","category":"Status","power":-1,"accuracy":-1,"pp":15,"description":"User copies the opponent's Ability."},"sand tomb":{"name":"Sand Tomb","type":"Ground","category":"Physical","power":35,"accuracy":85,"pp":15,"description":"Traps opponent, damaging them for 4-5 turns."},"secret power":{"name":"Secret Power","type":"Normal","category":"Physical","power":70,"accuracy":100,"pp":20,"description":"Effects of the attack vary with the location."},"shadow punch":{"name":"Shadow Punch","type":"Ghost","category":"Physical","power":60,"accuracy":-1,"pp":20,"description":"Ignores Accuracy and Evasiveness."},"sheer cold":{"name":"Sheer Cold","type":"Ice","category":"Special","power":-1,"accuracy":-1,"pp":5,"description":"One-Hit-KO, if it hits."},"shock wave":{"name":"Shock Wave","type":"Electric","category":"Special","power":60,"accuracy":-1,"pp":20,"description":"Ignores Accuracy and Evasiveness."},"signal beam":{"name":"Signal Beam","type":"Bug","category":"Special","power":75,"accuracy":100,"pp":15,"description":"May confuse opponent."},"silver wind":{"name":"Silver Wind","type":"Bug","category":"Special","power":60,"accuracy":100,"pp":5,"description":"May raise all stats of user at once."},"skill swap":{"name":"Skill Swap","type":"Psychic","category":"Status","power":-1,"accuracy":-1,"pp":10,"description":"The user swaps Abilities with the opponent."},"sky uppercut":{"name":"Sky Uppercut","type":"Fighting","category":"Physical","power":85,"accuracy":90,"pp":15,"description":"Hits the opponent, even during Fly."},"slack off":{"name":"Slack Off","type":"Normal","category":"Status","power":-1,"accuracy":-1,"pp":10,"description":"User recovers half its max HP."},"smelling salts":{"name":"Smelling Salts","type":"Normal","category":"Physical","power":70,"accuracy":100,"pp":10,"description":"Power doubles if opponent is paralyzed, but cures it."},"snatch":{"name":"Snatch","type":"Dark","category":"Status","power":-1,"accuracy":-1,"pp":10,"description":"Steals the effects of the opponent's next move."},"spit up":{"name":"Spit Up","type":"Normal","category":"Special","power":-1,"accuracy":100,"pp":10,"description":"Power depends on how many times the user performed Stockpile."},"stockpile":{"name":"Stockpile","type":"Normal","category":"Status","power":-1,"accuracy":-1,"pp":20,"description":"Stores energy for use with Spit Up and Swallow."},"superpower":{"name":"Superpower","type":"Fighting","category":"Physical","power":120,"accuracy":100,"pp":5,"description":"Lowers user's Attack and Defense."},"swallow":{"name":"Swallow","type":"Normal","category":"Status","power":-1,"accuracy":-1,"pp":10,"description":"The more times the user has performed Stockpile, the more HP is recovered."},"tail glow":{"name":"Tail Glow","type":"Bug","category":"Status","power":-1,"accuracy":-1,"pp":20,"description":"Drastically raises user's Special Attack."},"taunt":{"name":"Taunt","type":"Dark","category":"Status","power":-1,"accuracy":100,"pp":20,"description":"Opponent can only use moves that attack."},"teeter dance":{"name":"Teeter Dance","type":"Normal","category":"Status","power":-1,"accuracy":100,"pp":20,"description":"Confuses all Pokémon."},"tickle":{"name":"Tickle","type":"Normal","category":"Status","power":-1,"accuracy":100,"pp":20,"description":"Lowers opponent's Attack and Defense."},"torment":{"name":"Torment","type":"Dark","category":"Status","power":-1,"accuracy":100,"pp":15,"description":"Opponent cannot use the same move in a row."},"trick":{"name":"Trick","type":"Psychic","category":"Status","power":-1,"accuracy":100,"pp":10,"description":"Swaps held items with the opponent."},"uproar":{"name":"Uproar","type":"Normal","category":"Special","power":90,"accuracy":100,"pp":10,"description":"User attacks for 3 turns and prevents sleep."},"volt tackle":{"name":"Volt Tackle","type":"Electric","category":"Physical","power":120,"accuracy":100,"pp":15,"description":"User receives recoil damage. May paralyze opponent."},"water pulse":{"name":"Water Pulse","type":"Water","category":"Special","power":60,"accuracy":100,"pp":20,"description":"May confuse opponent."},"water sport":{"name":"Water Sport","type":"Water","category":"Status","power":-1,"accuracy":-1,"pp":15,"description":"Weakens the power of Fire-type moves."},"water spout":{"name":"Water Spout","type":"Water","category":"Special","power":150,"accuracy":100,"pp":5,"description":"The higher the user's HP, the higher the damage caused."},"weather ball":{"name":"Weather Ball","type":"Normal","category":"Special","power":50,"accuracy":100,"pp":10,"description":"Move's power and type changes with the weather."},"will-o-wisp":{"name":"Will-O-Wisp","type":"Fire","category":"Status","power":-1,"accuracy":85,"pp":15,"description":"Burns opponent."},"wish":{"name":"Wish","type":"Normal","category":"Status","power":-1,"accuracy":-1,"pp":10,"description":"The user recovers HP in the following turn."},"yawn":{"name":"Yawn","type":"Normal","category":"Status","power":-1,"accuracy":-1,"pp":10,"description":"Puts opponent to sleep in the next turn."}}